core/__init__.py
core/csvtojson.py
hive_csv2json-0.1.dev2.dist-info/METADATA
hive_csv2json-0.1.dev2.dist-info/WHEEL
hive_csv2json-0.1.dev2.dist-info/entry_points.txt
hive_csv2json-0.1.dev2.dist-info/top_level.txt
hive_csv2json-0.1.dev2.dist-info/RECORD
